{
  "generated_at": "2026-01-23T03:34:38.288Z",
  "emits_only_issues": true,
  "issues_breakdown": {
    "non_geocodable_address": 3,
    "missing_address": 17
  },
  "totals": {
    "total_services": 196,
    "missing_coordinates_any": 58,
    "address_required_missing_address": 17,
    "address_required_non_geocodable_address": 3,
    "coordinates_required_missing_coordinates": 0
  },
  "items": [
    {
      "id": "kingston-interval-house",
      "name": "Kingston Interval House",
      "intent_category": "Crisis",
      "scope": "kingston",
      "url": "https://kingstonintervalhouse.com",
      "phone": "613-546-1777 (Crisis Line)",
      "status": "Active",
      "published": null,
      "virtual_delivery": null,
      "address": "P.O. Box 21042, Kingston, ON K7L 5P5 (Mailing Only)",
      "has_coordinates": true,
      "address_required": true,
      "address_geocodable": false,
      "coordinates_required": false,
      "issues": ["non_geocodable_address"]
    },
    {
      "id": "lionhearts-fresh-food-market",
      "name": "Lionhearts Fresh Food Market",
      "intent_category": "Food",
      "scope": "kingston",
      "url": "https://lionhearts.ca",
      "phone": "613-766-0664",
      "status": "Active",
      "published": null,
      "virtual_delivery": null,
      "address": "Various Locations (Pop-up)",
      "has_coordinates": false,
      "address_required": true,
      "address_geocodable": false,
      "coordinates_required": false,
      "issues": ["non_geocodable_address"]
    },
    {
      "id": "kfpl-rideau-heights",
      "name": "KFPL - Rideau Heights Branch",
      "intent_category": "Community",
      "scope": "kingston",
      "url": "https://www.kfpl.ca",
      "phone": null,
      "status": null,
      "published": null,
      "virtual_delivery": null,
      "address": null,
      "has_coordinates": false,
      "address_required": true,
      "address_geocodable": false,
      "coordinates_required": false,
      "issues": ["missing_address"]
    },
    {
      "id": "kingston-pregnancy-care",
      "name": "Kingston Pregnancy Care Centre",
      "intent_category": "Health",
      "scope": "kingston",
      "url": "https://kingstonpcc.com",
      "phone": null,
      "status": null,
      "published": null,
      "virtual_delivery": null,
      "address": null,
      "has_coordinates": false,
      "address_required": true,
      "address_geocodable": false,
      "coordinates_required": false,
      "issues": ["missing_address"]
    },
    {
      "id": "alzheimer-society-kfla",
      "name": "Alzheimer Society KFL&A",
      "intent_category": "Health",
      "scope": "kingston",
      "url": "https://alzheimer.ca/kfla",
      "phone": null,
      "status": null,
      "published": null,
      "virtual_delivery": null,
      "address": null,
      "has_coordinates": false,
      "address_required": true,
      "address_geocodable": false,
      "coordinates_required": false,
      "issues": ["missing_address"]
    },
    {
      "id": "autism-ontario-east",
      "name": "Autism Ontario (East Region)",
      "intent_category": "Health",
      "scope": "kingston",
      "url": "https://www.autismontario.com",
      "phone": null,
      "status": null,
      "published": null,
      "virtual_delivery": null,
      "address": null,
      "has_coordinates": false,
      "address_required": true,
      "address_geocodable": false,
      "coordinates_required": false,
      "issues": ["missing_address"]
    },
    {
      "id": "cnib-kingston",
      "name": "CNIB Foundation Kingston",
      "intent_category": "Health",
      "scope": "kingston",
      "url": "https://cnib.ca",
      "phone": null,
      "status": null,
      "published": null,
      "virtual_delivery": null,
      "address": null,
      "has_coordinates": false,
      "address_required": true,
      "address_geocodable": false,
      "coordinates_required": false,
      "issues": ["missing_address"]
    },
    {
      "id": "tnet-kingston",
      "name": "TransFamily Kingston",
      "intent_category": "Community",
      "scope": "kingston",
      "url": "https://transfamilykingston.com",
      "phone": null,
      "status": "Active",
      "published": null,
      "virtual_delivery": null,
      "address": "Downtown Kingston (Contact for location)",
      "has_coordinates": true,
      "address_required": true,
      "address_geocodable": false,
      "coordinates_required": false,
      "issues": ["non_geocodable_address"]
    },
    {
      "id": "kfla-children-services",
      "name": "KFL&A Children's Services",
      "intent_category": "Community",
      "scope": "kingston",
      "url": "https://www.cityofkingston.ca",
      "phone": null,
      "status": null,
      "published": null,
      "virtual_delivery": null,
      "address": null,
      "has_coordinates": false,
      "address_required": true,
      "address_geocodable": false,
      "coordinates_required": false,
      "issues": ["missing_address"]
    },
    {
      "id": "kingston-east-community-centre",
      "name": "Kingston East Community Centre",
      "intent_category": "Wellness",
      "scope": "kingston",
      "url": "https://www.cityofkingston.ca",
      "phone": null,
      "status": null,
      "published": null,
      "virtual_delivery": null,
      "address": null,
      "has_coordinates": false,
      "address_required": true,
      "address_geocodable": false,
      "coordinates_required": false,
      "issues": ["missing_address"]
    },
    {
      "id": "kingston-humane-society",
      "name": "Kingston Humane Society",
      "intent_category": "Community",
      "scope": "kingston",
      "url": "https://kingstonhumanesociety.ca",
      "phone": null,
      "status": null,
      "published": null,
      "virtual_delivery": null,
      "address": null,
      "has_coordinates": false,
      "address_required": true,
      "address_geocodable": false,
      "coordinates_required": false,
      "issues": ["missing_address"]
    },
    {
      "id": "st-john-ambulance-kingston",
      "name": "St. John Ambulance",
      "intent_category": "Health",
      "scope": "kingston",
      "url": "https://www.sja.ca",
      "phone": null,
      "status": null,
      "published": null,
      "virtual_delivery": null,
      "address": null,
      "has_coordinates": false,
      "address_required": true,
      "address_geocodable": false,
      "coordinates_required": false,
      "issues": ["missing_address"]
    },
    {
      "id": "red-cross-kingston",
      "name": "Canadian Red Cross - Kingston",
      "intent_category": "Community",
      "scope": "kingston",
      "url": "https://www.redcross.ca",
      "phone": null,
      "status": null,
      "published": null,
      "virtual_delivery": null,
      "address": null,
      "has_coordinates": false,
      "address_required": true,
      "address_geocodable": false,
      "coordinates_required": false,
      "issues": ["missing_address"]
    },
    {
      "id": "habitat-for-humanity-kingston",
      "name": "Habitat for Humanity Kingston",
      "intent_category": "Housing",
      "scope": "kingston",
      "url": "https://habitatkingston.com",
      "phone": null,
      "status": null,
      "published": null,
      "virtual_delivery": null,
      "address": null,
      "has_coordinates": false,
      "address_required": true,
      "address_geocodable": false,
      "coordinates_required": false,
      "issues": ["missing_address"]
    },
    {
      "id": "odsp-kingston",
      "name": "ODSP Kingston Office",
      "intent_category": "Financial",
      "scope": "kingston",
      "url": "https://www.ontario.ca",
      "phone": null,
      "status": null,
      "published": null,
      "virtual_delivery": null,
      "address": null,
      "has_coordinates": false,
      "address_required": true,
      "address_geocodable": false,
      "coordinates_required": false,
      "issues": ["missing_address"]
    },
    {
      "id": "service-canada-kingston",
      "name": "Service Canada Centre",
      "intent_category": "Financial",
      "scope": "kingston",
      "url": "https://www.canada.ca",
      "phone": null,
      "status": null,
      "published": null,
      "virtual_delivery": null,
      "address": null,
      "has_coordinates": false,
      "address_required": true,
      "address_geocodable": false,
      "coordinates_required": false,
      "issues": ["missing_address"]
    },
    {
      "id": "service-ontario-kingston",
      "name": "ServiceOntario",
      "intent_category": "Community",
      "scope": "kingston",
      "url": "https://www.ontario.ca",
      "phone": null,
      "status": null,
      "published": null,
      "virtual_delivery": null,
      "address": null,
      "has_coordinates": false,
      "address_required": true,
      "address_geocodable": false,
      "coordinates_required": false,
      "issues": ["missing_address"]
    },
    {
      "id": "kingston-police-non-emerg",
      "name": "Kingston Police (Non-Emergency)",
      "intent_category": "Community",
      "scope": "kingston",
      "url": "https://www.kpf.ca",
      "phone": null,
      "status": null,
      "published": null,
      "virtual_delivery": null,
      "address": null,
      "has_coordinates": false,
      "address_required": true,
      "address_geocodable": false,
      "coordinates_required": false,
      "issues": ["missing_address"]
    },
    {
      "id": "opp-frontenac",
      "name": "OPP Frontenac Detachment",
      "intent_category": "Community",
      "scope": "kingston",
      "url": "https://www.opp.ca",
      "phone": null,
      "status": null,
      "published": null,
      "virtual_delivery": null,
      "address": null,
      "has_coordinates": false,
      "address_required": true,
      "address_geocodable": false,
      "coordinates_required": false,
      "issues": ["missing_address"]
    },
    {
      "id": "coast-mental-health",
      "name": "COAST (Crisis Outreach)",
      "intent_category": "Crisis",
      "scope": "kingston",
      "url": "https://amhs-kfla.ca",
      "phone": "613-544-4229",
      "status": null,
      "published": null,
      "virtual_delivery": null,
      "address": null,
      "has_coordinates": false,
      "address_required": true,
      "address_geocodable": false,
      "coordinates_required": false,
      "issues": ["missing_address"]
    }
  ]
}
